tree_sitter_scala/__init__.py
tree_sitter_scala/__init__.pyi
tree_sitter_scala/_binding.pyd
tree_sitter_scala/binding.c
tree_sitter_scala/py.typed
tree_sitter_scala/queries/highlights.scm
tree_sitter_scala/queries/indents.scm
tree_sitter_scala/queries/locals.scm
tree_sitter_scala/queries/tags.scm
tree_sitter_scala-0.24.0.dist-info/licenses/LICENSE
tree_sitter_scala-0.24.0.dist-info/METADATA
tree_sitter_scala-0.24.0.dist-info/WHEEL
tree_sitter_scala-0.24.0.dist-info/top_level.txt
tree_sitter_scala-0.24.0.dist-info/RECORD
