Metadata-Version: 2.4
Name: tree-sitter-scala
Version: 0.24.0
Summary: Scala grammar for tree-sitter
Author-email: Max Brunsfeld <maxbrunsfeld@gmail.com>
License: MIT
Project-URL: Homepage, https://github.com/tree-sitter/tree-sitter-scala
Keywords: incremental,parsing,tree-sitter,scala
Classifier: Intended Audience :: Developers
Classifier: License :: OSI Approved :: MIT License
Classifier: Topic :: Software Development :: Compilers
Classifier: Topic :: Text Processing :: Linguistic
Classifier: Typing :: Typed
Requires-Python: >=3.9
License-File: LICENSE
Provides-Extra: core
Requires-Dist: tree-sitter~=0.22; extra == "core"
Dynamic: license-file
